{
	"_id": "0iBa7JQeRybY0eZI",
	"_key": "!items!0iBa7JQeRybY0eZI",
	"effects": [
	],
	"folder": null,
	"img": "icons/environment/people/group.webp",
	"name": "Shadow elf",
	"system": {
		"description": "<p>Lithe, stealthy elf who have embraced the the realm of shadows.</p>",
		"languages": {
			"common": 0,
			"fixed": [
				"Compendium.shadowdark.languages.Item.DQzHvoMWSZ0eiRWP",
				"Compendium.shadowdark.languages.Item.wABiw5UhzG2G8Kpa"
			],
			"rare": 0,
			"select": 0,
			"selectOptions": [
			]
		},
		"nameTable": "",
		"predefinedEffects": "",
		"randomWeight": 1,
		"source": {
			"title": "ekiz"
		},
		"talentChoiceCount": 1,
		"talents": [
			"Compendium.shadowdark.talents.Item.nG6YGc8XEQ0N7bem"
		]
	},
	"type": "Ancestry"
}
